cython_chess.cpython-310-i386-linux-gnu.so
cython_chess.libs/libgcc_s-887de51c.so.1
cython_chess.libs/libstdc++-d6415257.so.6.0.33
src/__init__.py
src/cython_chess.cpp
src/cython_chess.pyx
src/cython_chess_backend.cpp
src/cython_chess_backend.h
cython_chess-0.3.dist-info/METADATA
cython_chess-0.3.dist-info/WHEEL
cython_chess-0.3.dist-info/top_level.txt
cython_chess-0.3.dist-info/RECORD
cython_chess-0.3.dist-info/licenses/LICENSE
